birthday_surprise/__init__.py
birthday_surprise/main.py
birthday_surprise/assets/birthday-song.wav
birthday_surprise/assets/card.png
birthday_surprise-1.0.1.dist-info/METADATA
birthday_surprise-1.0.1.dist-info/WHEEL
birthday_surprise-1.0.1.dist-info/entry_points.txt
birthday_surprise-1.0.1.dist-info/top_level.txt
birthday_surprise-1.0.1.dist-info/RECORD
