Metadata-Version: 2.4
Name: birthday_surprise
Version: 1.0.1
Summary: A CLI birthday surprise package
Author: Devika Harshey
Requires-Python: >=3.8
Requires-Dist: colorama
Requires-Dist: pyfiglet
Requires-Dist: requests
Dynamic: author
Dynamic: requires-dist
Dynamic: requires-python
Dynamic: summary
